gpg_keyring/__init__.py
gpg_keyring-0.1.1.dist-info/licenses/LICENSE
gpg_keyring-0.1.1.dist-info/METADATA
gpg_keyring-0.1.1.dist-info/WHEEL
gpg_keyring-0.1.1.dist-info/entry_points.txt
gpg_keyring-0.1.1.dist-info/top_level.txt
gpg_keyring-0.1.1.dist-info/RECORD
